ussclicore/__init__.py
ussclicore/argumentParser.py
ussclicore/cmd.py
ussclicore/utils/__init__.py
ussclicore/utils/ascii_bar_graph.py
ussclicore/utils/download_utils.py
ussclicore/utils/generics_utils.py
ussclicore/utils/printer.py
ussclicore/utils/progressbar_widget.py
ussclicore-1.0.11.dist-info/DESCRIPTION.rst
ussclicore-1.0.11.dist-info/METADATA
ussclicore-1.0.11.dist-info/RECORD
ussclicore-1.0.11.dist-info/WHEEL
ussclicore-1.0.11.dist-info/metadata.json
ussclicore-1.0.11.dist-info/top_level.txt
