Metadata-Version: 2.0
Name: ussclicore
Version: 1.0.11
Summary: UShareSoft cli core module
Home-page: UNKNOWN
Author: Joris Bremond
Author-email: joris.bremond@usharesoft.com
License: Apache License 2.0
Platform: UNKNOWN
Classifier: Development Status :: 5 - Production/Stable
Classifier: Environment :: Console
Classifier: Intended Audience :: Developers
Classifier: Intended Audience :: System Administrators
Classifier: Natural Language :: English
Classifier: Operating System :: MacOS :: MacOS X
Classifier: Operating System :: Microsoft :: Windows
Classifier: Operating System :: POSIX
Classifier: License :: OSI Approved :: Apache Software License
Classifier: Programming Language :: Python
Classifier: Programming Language :: Python :: 2.6
Classifier: Programming Language :: Python :: 2.7
Requires-Dist: cmd2 (==0.6.7)
Requires-Dist: argparse
Requires-Dist: progressbar (==2.3)
Requires-Dist: termcolor (==1.1.0)
Requires-Dist: hurry.filesize (==0.9)
Requires-Dist: pyyaml (==3.12)
